pyxpg-0.0.5.dist-info/RECORD
pyxpg-0.0.5.dist-info/WHEEL
pyxpg-0.0.5.dist-info/METADATA
pyxpg/__init__.pyi
pyxpg/__init__.py
pyxpg/_pyxpg.cpython-310-darwin.so
pyxpg/py.typed
pyxpg/slang/__init__.pyi
pyxpg/slang/__init__.py
pyxpg/slang/py.typed
pyxpg/imgui/__init__.pyi
pyxpg/imgui/__init__.py
pyxpg/imgui/py.typed
