Metadata-Version: 2.1
Name: pyxpg
Version: 0.0.5
Summary: XPG python bindings
Author-Email: Dario Mylonopoulos <ramenguy99@gmail.com>
Classifier: License :: OSI Approved :: MIT License
Project-URL: Homepage, https://github.com/ramenguy99/xpg
Requires-Python: >=3.8
